listener/__init__.py
robotLocalization/__init__.py
robotLocalization/analyze.py
robotLocalization/api.py
robotLocalization/apis.py
robotLocalization/get_variables.py
robotLocalization/load_properties.py
robotLocalization/loader.py
robotLocalization/loader_xml.py
robotLocalization/robotLocalization.py
robotLocalization/testit.py
robotLocalization/traverse_tree.py
robotLocalization/util.py
robotLocalization/testit/__init__.py
robotLocalization/testit/api.py
robotLocalization/testit/testit.py
robotLocalization-0.9.1.dist-info/LICENSE
robotLocalization-0.9.1.dist-info/METADATA
robotLocalization-0.9.1.dist-info/WHEEL
robotLocalization-0.9.1.dist-info/entry_points.txt
robotLocalization-0.9.1.dist-info/top_level.txt
robotLocalization-0.9.1.dist-info/RECORD
