Metadata-Version: 2.1
Name: robotLocalization
Version: 0.9.1
Summary: Robot Framework Internationalization
Home-page: UNKNOWN
Author: Shinichiro Kayano
License: MIT
Keywords: localization cicd test automation
Platform: UNKNOWN
Classifier: License :: OSI Approved :: MIT License
Classifier: Environment :: Console
Classifier: Development Status :: 3 - Alpha
Classifier: Programming Language :: Python :: 3.7
Classifier: Programming Language :: Python :: 3.8
Classifier: Framework :: Robot Framework :: Tool
Classifier: Topic :: Software Development :: Localization
Requires-Dist: jproperties (>=2.1.1)
Requires-Dist: requests (>=2.22.0)
Provides-Extra: dev
Requires-Dist: pytest ; extra == 'dev'
Requires-Dist: docutils ; extra == 'dev'
Requires-Dist: pygments ; extra == 'dev'
Provides-Extra: optional
Requires-Dist: robotframework ; extra == 'optional'
Requires-Dist: robotframework-seleniumlibrary ; extra == 'optional'
Requires-Dist: robotframework-autorecorder ; extra == 'optional'
Requires-Dist: robotframework-requests ; extra == 'optional'
Requires-Dist: opencv-python ; extra == 'optional'
